Metadata-Version: 2.1
Name: xpath_writer
Version: 1.0.1
Summary: A Python package for writing relative XPath expressions and make XPath Excel file.
Home-page: https://github.com/pagidireddy/
Author: Pagidireddy Prasanth Reddy
Author-email: tradetrontest@gmail.com
License: MIT
Keywords: xpath,xpath generator,xpath writer,xpath parser
Classifier: Programming Language :: Python :: 3
Classifier: License :: OSI Approved :: MIT License
Classifier: Operating System :: OS Independent
Requires-Python: >=3.6
Requires-Dist: requests
Requires-Dist: beautifulsoup4
Requires-Dist: pandas
Requires-Dist: openpyxl
